bos/__init__.py
bos/identity_layer.py
bos/role_manager.py
conscious_bridge-1.0.4.dist-info/licenses/LICENSE-CC-BY.txt
conscious_bridge-1.0.4.dist-info/licenses/LICENSE-MIT.txt
core/__init__.py
core/attention_metrics.py
core/bridge_dynamics.py
core/bridge_map.py
core/language_centers.py
core/phi_calculator.py
engine/__init__.py
engine/conscious_law.py
engine/stability_monitor.py
engine/temperature_adapter.py
utils/__init__.py
utils/metrics.py
utils/token_analysis.py
conscious_bridge-1.0.4.dist-info/METADATA
conscious_bridge-1.0.4.dist-info/WHEEL
conscious_bridge-1.0.4.dist-info/top_level.txt
conscious_bridge-1.0.4.dist-info/RECORD
