Metadata-Version: 2.4
Name: conscious-bridge
Version: 1.0.4
Summary: Transitional Geometry between Aristotelian and Platonic Logic in AI
Author-email: Samir Baladi <riteofrenaissance@proton.me>
License: MIT
Project-URL: Homepage, https://github.com/riteofrenaissance/Conscious-Bridge-Law
Requires-Python: >=3.8
License-File: LICENSE-CC-BY.txt
License-File: LICENSE-MIT.txt
Requires-Dist: numpy>=1.21.0
Requires-Dist: scipy>=1.7.0
Provides-Extra: ai
Requires-Dist: torch>=1.9.0; extra == "ai"
Requires-Dist: transformers>=4.12.0; extra == "ai"
Provides-Extra: full
Requires-Dist: torch>=1.9.0; extra == "full"
Requires-Dist: transformers>=4.12.0; extra == "full"
Requires-Dist: matplotlib>=3.5.0; extra == "full"
Requires-Dist: pandas>=1.3.0; extra == "full"
Provides-Extra: dev
Requires-Dist: pytest>=7.0.0; extra == "dev"
Requires-Dist: black>=22.0.0; extra == "dev"
Requires-Dist: flake8>=5.0.0; extra == "dev"
Dynamic: license-file
